glcs/__init__.py
glcs/assignment.py
glcs/command_line.py
glcs/config.py
glcs/constants.py
glcs/course.py
glcs/group.py
glcs/main.py
glcs/project.py
glcs/storage.py
glcs/student.py
glcs/utils.py
glcs/Mimir/Main.java
glcs/Mimir/Submit-student-project.py
glcs/Mimir/Submit-student-project.sh
glcs/templates/verify_output.html
glcs-0.1.6.dist-info/LICENSE
glcs-0.1.6.dist-info/METADATA
glcs-0.1.6.dist-info/WHEEL
glcs-0.1.6.dist-info/entry_points.txt
glcs-0.1.6.dist-info/top_level.txt
glcs-0.1.6.dist-info/RECORD
