Metadata-Version: 2.1
Name: glcs
Version: 0.1.6
Summary: A utility for integrating GitLab into CS courses
Home-page: UNKNOWN
Author: Austin Fishbaugh
Author-email: amf2015@wildcats.unh.edu
License: UNKNOWN
Platform: UNKNOWN
Classifier: Programming Language :: Python :: 3
Classifier: License :: OSI Approved :: MIT License
Classifier: Operating System :: OS Independent
Requires-Dist: python-gitlab (>=1.6.0)
Requires-Dist: mimir-cli
Requires-Dist: flask
Requires-Dist: jinja2
Requires-Dist: xdg
Requires-Dist: argparse
Requires-Dist: pyreadline ; platform_system == "Windows"
